lf/__init__.py
lf/calibration.py
lf/calibration_lut.py
lf/crawler.py
lf/polar.py
lf/txrx.py
lf/utils.py
lf/data/__init__.py
lf/data/rx.py
lf/data/rxquality.py
lf/data/table.py
lf-0.1.9.dist-info/LICENSE
lf-0.1.9.dist-info/METADATA
lf-0.1.9.dist-info/WHEEL
lf-0.1.9.dist-info/top_level.txt
lf-0.1.9.dist-info/RECORD
