Metadata-Version: 2.1
Name: lf
Version: 0.1.9
Summary: Tools for interacting with GT's LF AWESOME Receiver data
Home-page: https://github.gatech.edu/LF-Group/lfdata
Author: David Richardson
Author-email: drichardson42@gatech.edu
Classifier: Programming Language :: Python :: 3
Classifier: Programming Language :: Python :: 3.6
Classifier: Programming Language :: Python :: 3.7
Classifier: License :: OSI Approved :: GNU General Public License v3 or later (GPLv3+)
Classifier: Development Status :: 3 - Alpha
Classifier: Intended Audience :: Science/Research
License-File: LICENSE
Requires-Dist: scipy
Requires-Dist: numpy
Requires-Dist: scikit-learn
Requires-Dist: geographiclib
Requires-Dist: pandas
Requires-Dist: pysolar (>=0.8)
Requires-Dist: matplotlib
Requires-Dist: datetime
Provides-Extra: dev
Requires-Dist: twine ; extra == 'dev'
Requires-Dist: sphinx (==3.2.1) ; extra == 'dev'
Provides-Extra: docs
Requires-Dist: sphinx (==3.2.1) ; extra == 'docs'
